cs/queues.py
cs_queues-20250426.dist-info/WHEEL
cs_queues-20250426.dist-info/METADATA
cs_queues-20250426.dist-info/RECORD
